openstackdocstheme/__init__.py
openstackdocstheme/ext.py
openstackdocstheme/page_context.py
openstackdocstheme/paths.py
openstackdocstheme/version.py
openstackdocstheme/theme/openstackdocs/css.html
openstackdocstheme/theme/openstackdocs/footer.html
openstackdocstheme/theme/openstackdocs/header.html
openstackdocstheme/theme/openstackdocs/layout.html
openstackdocstheme/theme/openstackdocs/license_cc.html
openstackdocstheme/theme/openstackdocs/localtoc.html
openstackdocstheme/theme/openstackdocs/os_search.html
openstackdocstheme/theme/openstackdocs/os_search_install.html
openstackdocstheme/theme/openstackdocs/os_search_mobile.html
openstackdocstheme/theme/openstackdocs/script_footer.html
openstackdocstheme/theme/openstackdocs/script_search.html
openstackdocstheme/theme/openstackdocs/search.html
openstackdocstheme/theme/openstackdocs/sidebartoc.html
openstackdocstheme/theme/openstackdocs/sidebartoc_menu.html
openstackdocstheme/theme/openstackdocs/sidebartoc_menu_apiref.html
openstackdocstheme/theme/openstackdocs/theme.conf
openstackdocstheme/theme/openstackdocs/titlerow.html
openstackdocstheme/theme/openstackdocs/static/favicon.ico
openstackdocstheme/theme/openstackdocs/static/css/bootstrap.css
openstackdocstheme/theme/openstackdocs/static/css/bootstrap.css.map
openstackdocstheme/theme/openstackdocs/static/css/bootstrap.min.css
openstackdocstheme/theme/openstackdocs/static/css/bootstrap.min.css.map
openstackdocstheme/theme/openstackdocs/static/css/combined.css
openstackdocstheme/theme/openstackdocs/static/css/font-awesome.css
openstackdocstheme/theme/openstackdocs/static/css/font-awesome.min.css
openstackdocstheme/theme/openstackdocs/static/css/search.css
openstackdocstheme/theme/openstackdocs/static/fonts/.gitkeep
openstackdocstheme/theme/openstackdocs/static/fonts/FontAwesome.otf
openstackdocstheme/theme/openstackdocs/static/fonts/fontawesome-webfont.eot
openstackdocstheme/theme/openstackdocs/static/fonts/fontawesome-webfont.svg
openstackdocstheme-3.5.0.dist-info/AUTHORS
openstackdocstheme-3.5.0.dist-info/LICENSE
openstackdocstheme-3.5.0.dist-info/METADATA
openstackdocstheme-3.5.0.dist-info/WHEEL
openstackdocstheme-3.5.0.dist-info/pbr.json
openstackdocstheme-3.5.0.dist-info/top_level.txt
openstackdocstheme-3.5.0.dist-info/RECORD
